[{"_path":"/fr/components/prose/code-blocks","_dir":"prose","_draft":false,"_partial":false,"_locale":"","title":"Bloc de Code","description":"Une présentation de tous les variants de blocs de code.","icon":"lucide:square-code","_type":"markdown","_id":"content:fr:2.components:1.prose:2.code-blocks.md","_source":"content","_file":"fr/2.components/1.prose/2.code-blocks.md","_stem":"fr/2.components/1.prose/2.code-blocks","_extension":"md"},{"_path":"/fr/components/docs/alert","_dir":"docs","_draft":false,"_partial":false,"_locale":"","title":"Alert","description":"","icon":"lucide:triangle-alert","badges":[{"value":"Docus","to":"https://docus.dev/api/components#alert","target":"_blank"},{"value":"Source","icon":"lucide:code","to":"https://github.com/ZTL-UwU/shadcn-docs-nuxt/blob/main/components/content/Alert.vue","target":"_blank"}],"_type":"markdown","_id":"content:fr:2.components:2.docs:alert.md","_source":"content","_file":"fr/2.components/2.docs/alert.md","_stem":"fr/2.components/2.docs/alert","_extension":"md"}]